fuzzy_controller/__init__.py
fuzzy_controller/fuzzy_logic.py
fuzzy_controller/utils.py
fuzzy_controller/visualization.py
fuzzy_controller-0.1.1.dist-info/LICENSE
fuzzy_controller-0.1.1.dist-info/METADATA
fuzzy_controller-0.1.1.dist-info/WHEEL
fuzzy_controller-0.1.1.dist-info/top_level.txt
fuzzy_controller-0.1.1.dist-info/RECORD
